[
  {
    "hidden_at": "2024-08-31T05:10:12.000Z",
    "type": "show",
    "show": {
      "title": "Selling Sunset",
      "year": 2019,
      "ids": {
        "trakt": 145635,
        "slug": "selling-sunset",
        "tvdb": 361394,
        "imdb": "tt9817298",
        "tmdb": 87826,
        "tvrage": null
      }
    }
  },
  {
    "hidden_at": "2024-08-31T05:10:03.000Z",
    "type": "show",
    "show": {
      "title": "NieR:Automata Ver1.1a",
      "year": 2023,
      "ids": {
        "trakt": 193608,
        "slug": "nier-automata-ver1-1a",
        "tvdb": 416998,
        "imdb": "tt18311412",
        "tmdb": 158373,
        "tvrage": null
      }
    }
  },
  {
    "hidden_at": "2023-10-19T00:44:00.000Z",
    "type": "show",
    "show": {
      "title": "The Daily Show",
      "year": 1996,
      "ids": {
        "trakt": 2211,
        "slug": "the-daily-show",
        "tvdb": 71256,
        "imdb": "tt0115147",
        "tmdb": 2224,
        "tvrage": null
      }
    }
  },
  {
    "hidden_at": "2023-10-14T15:48:36.000Z",
    "type": "show",
    "show": {
      "title": "The Late Show with Stephen Colbert",
      "year": 2015,
      "ids": {
        "trakt": 93737,
        "slug": "the-late-show-with-stephen-colbert",
        "tvdb": 289574,
        "imdb": "tt3697842",
        "tmdb": 63770,
        "tvrage": null
      }
    }
  },
  {
    "hidden_at": "2023-10-14T15:48:33.000Z",
    "type": "show",
    "show": {
      "title": "Last Week Tonight with John Oliver",
      "year": 2014,
      "ids": {
        "trakt": 60267,
        "slug": "last-week-tonight-with-john-oliver",
        "tvdb": 278518,
        "imdb": "tt3530232",
        "tmdb": 60694,
        "tvrage": null
      }
    }
  }
]
