[
  {
    "show": {
      "title": "Long Way Home",
      "year": 2025,
      "ids": {
        "trakt": 253389,
        "slug": "long-way-home-2025",
        "tvdb": 453705,
        "imdb": "tt33096033",
        "tmdb": 262594,
        "tvrage": null
      }
    },
    "progress": {
      "aired": 5,
      "completed": 2,
      "hidden": 0,
      "last_watched_at": "2025-06-05T07:20:34.000Z",
      "reset_at": null,
      "stats": {
        "play_count": 2,
        "minutes_left": 0,
        "minutes_watched": 0
      },
      "next_episode": {
        "season": 1,
        "number": 3,
        "title": "Survive the Ride",
        "ids": {
          "trakt": 12220763,
          "tvdb": 10653337,
          "imdb": "tt36687782",
          "tmdb": 5938538,
          "tvrage": null
        }
      },
      "last_episode": {
        "season": 1,
        "number": 2,
        "title": "Route Canal",
        "ids": {
          "trakt": 12220762,
          "tvdb": 10653336,
          "imdb": "tt36687780",
          "tmdb": 5938537,
          "tvrage": null
        }
      }
    }
  },
  {
    "show": {
      "title": "MobLand",
      "year": 2025,
      "ids": {
        "trakt": 228595,
        "slug": "mobland",
        "tvdb": 446831,
        "imdb": "tt31510819",
        "tmdb": 247718,
        "tvrage": null
      }
    },
    "progress": {
      "aired": 10,
      "completed": 4,
      "hidden": 0,
      "last_watched_at": "2025-06-02T23:30:37.000Z",
      "reset_at": null,
      "stats": {
        "play_count": 4,
        "minutes_left": 0,
        "minutes_watched": 0
      },
      "next_episode": {
        "season": 1,
        "number": 5,
        "title": "Funeral for a Friend",
        "ids": {
          "trakt": 12855310,
          "tvdb": 10987397,
          "imdb": "tt32125919",
          "tmdb": 6009141,
          "tvrage": null
        }
      },
      "last_episode": {
        "season": 1,
        "number": 4,
        "title": "Rat Trap",
        "ids": {
          "trakt": 12855309,
          "tvdb": 10987396,
          "imdb": "tt32125921",
          "tmdb": 6009140,
          "tvrage": null
        }
      }
    }
  },
  {
    "show": {
      "title": "Welcome to Wrexham",
      "year": 2022,
      "ids": {
        "trakt": 191775,
        "slug": "welcome-to-wrexham",
        "tvdb": 403119,
        "imdb": "tt14674086",
        "tmdb": 126929,
        "tvrage": null
      }
    },
    "progress": {
      "aired": 45,
      "completed": 41,
      "hidden": 0,
      "last_watched_at": "2024-06-17T05:54:46.000Z",
      "reset_at": null,
      "stats": {
        "play_count": 41,
        "minutes_left": 0,
        "minutes_watched": 0
      },
      "next_episode": {
        "season": 4,
        "number": 1,
        "title": "All In?",
        "ids": {
          "trakt": 12777769,
          "tvdb": null,
          "imdb": "tt32368637",
          "tmdb": 5948526,
          "tvrage": null
        }
      },
      "last_episode": {
        "season": 3,
        "number": 8,
        "title": "Down to the Wire",
        "ids": {
          "trakt": 11874454,
          "tvdb": 10302917,
          "imdb": "tt31224611",
          "tmdb": 5348966,
          "tvrage": null
        }
      }
    }
  },
  {
    "show": {
      "title": "Rick and Morty",
      "year": 2013,
      "ids": {
        "trakt": 69829,
        "slug": "rick-and-morty",
        "tvdb": 275274,
        "imdb": "tt2861424",
        "tmdb": 60625,
        "tvrage": null
      }
    },
    "progress": {
      "aired": 73,
      "completed": 71,
      "hidden": 0,
      "last_watched_at": "2023-12-19T20:00:32.000Z",
      "reset_at": null,
      "stats": {
        "play_count": 71,
        "minutes_left": 0,
        "minutes_watched": 0
      },
      "next_episode": {
        "season": 8,
        "number": 1,
        "title": "Summer of All Fears",
        "ids": {
          "trakt": 12956006,
          "tvdb": 11074528,
          "imdb": "tt28608179",
          "tmdb": 6085790,
          "tvrage": null
        }
      },
      "last_episode": {
        "season": 7,
        "number": 10,
        "title": "Fear No Mort",
        "ids": {
          "trakt": 10853991,
          "tvdb": 9986641,
          "imdb": "tt29371876",
          "tmdb": 4694210,
          "tvrage": null
        }
      }
    }
  },
  {
    "show": {
      "title": "Poker Face",
      "year": 2023,
      "ids": {
        "trakt": 187032,
        "slug": "poker-face-2023",
        "tvdb": 398822,
        "imdb": "tt14269590",
        "tmdb": 120998,
        "tvrage": null
      }
    },
    "progress": {
      "aired": 17,
      "completed": 10,
      "hidden": 0,
      "last_watched_at": "2023-03-10T18:46:55.000Z",
      "reset_at": null,
      "stats": {
        "play_count": 11,
        "minutes_left": 0,
        "minutes_watched": 0
      },
      "next_episode": {
        "season": 2,
        "number": 1,
        "title": "The Game Is a Foot",
        "ids": {
          "trakt": 12605600,
          "tvdb": 11020991,
          "imdb": "tt26740933",
          "tmdb": 6041738,
          "tvrage": null
        }
      },
      "last_episode": {
        "season": 1,
        "number": 10,
        "title": "The Hook",
        "ids": {
          "trakt": 6817625,
          "tvdb": 9421259,
          "imdb": "tt19636674",
          "tmdb": 4026508,
          "tvrage": null
        }
      }
    }
  },
  {
    "show": {
      "title": "Nine Perfect Strangers",
      "year": 2021,
      "ids": {
        "trakt": 158087,
        "slug": "nine-perfect-strangers",
        "tvdb": 376815,
        "imdb": "tt8760932",
        "tmdb": 88989,
        "tvrage": null
      }
    },
    "progress": {
      "aired": 12,
      "completed": 8,
      "hidden": 0,
      "last_watched_at": "2021-09-23T03:07:01.000Z",
      "reset_at": null,
      "stats": {
        "play_count": 8,
        "minutes_left": 0,
        "minutes_watched": 0
      },
      "next_episode": {
        "season": 2,
        "number": 1,
        "title": "Zauberwald",
        "ids": {
          "trakt": 10807947,
          "tvdb": 11065376,
          "imdb": "tt20228152",
          "tmdb": 6093348,
          "tvrage": null
        }
      },
      "last_episode": {
        "season": 1,
        "number": 8,
        "title": "Ever After",
        "ids": {
          "trakt": 5454497,
          "tvdb": 8436206,
          "imdb": "tt12797270",
          "tmdb": 3203760,
          "tvrage": null
        }
      }
    }
  }
]
