[
  {
    "show": {
      "title": "007: Road to a Million",
      "year": 2023,
      "ids": {
        "trakt": 209558,
        "slug": "007-road-to-a-million",
        "tvdb": 418229,
        "imdb": "tt19049680",
        "tmdb": 234455,
        "tvrage": null
      }
    },
    "progress": {
      "aired": 16,
      "completed": 8,
      "hidden": 0,
      "last_watched_at": "2023-11-12T21:11:20.000Z",
      "reset_at": null,
      "stats": {
        "play_count": 8,
        "minutes_left": 0,
        "minutes_watched": 0
      },
      "next_episode": {
        "season": 2,
        "number": 1,
        "title": "Episode 1",
        "ids": {
          "trakt": 13352031,
          "tvdb": null,
          "imdb": null,
          "tmdb": 6406311,
          "tvrage": null
        }
      },
      "last_episode": {
        "season": 1,
        "number": 8,
        "title": "EPISODE EIGHT",
        "ids": {
          "trakt": 10891164,
          "tvdb": null,
          "imdb": null,
          "tmdb": 4715888,
          "tvrage": null
        }
      }
    }
  },
  {
    "show": {
      "title": "Peacemaker",
      "year": 2022,
      "ids": {
        "trakt": 169009,
        "slug": "peacemaker-2022",
        "tvdb": 391153,
        "imdb": "tt13146488",
        "tmdb": 110492,
        "tvrage": null
      }
    },
    "progress": {
      "aired": 9,
      "completed": 8,
      "hidden": 0,
      "last_watched_at": "2022-02-18T06:57:22.000Z",
      "reset_at": null,
      "stats": {
        "play_count": 8,
        "minutes_left": 0,
        "minutes_watched": 0
      },
      "next_episode": {
        "season": 2,
        "number": 1,
        "title": "The Ties That Grind",
        "ids": {
          "trakt": 12483930,
          "tvdb": 11071140,
          "imdb": "tt18263680",
          "tmdb": 6108954,
          "tvrage": null
        }
      },
      "last_episode": {
        "season": 1,
        "number": 8,
        "title": "It's Cow or Never",
        "ids": {
          "trakt": 4720836,
          "tvdb": 8869910,
          "imdb": "tt13152062",
          "tmdb": 2438363,
          "tvrage": null
        }
      }
    }
  }
]
